[
  {
    "title": "The Unparalleled Genius of John von Neumann",
    "url": "https://www.cantorsparadise.com/the-unparalleled-genius-of-john-von-neumann-791bb9f42a2d",
    "upvotes": 412,
    "author": "jdkee",
    "comments": 206,
    "link": "https://news.ycombinator.com/item?id=26695502"
  },
  {
    "title": "What defines a great company culture?",
    "url": "https://twitter.com/danrose999/status/1378393523213373440",
    "upvotes": 13,
    "author": "prostoalex",
    "comments": 12,
    "link": "https://news.ycombinator.com/item?id=26700186"
  },
  {
    "title": "7% of Americans don’t use the internet. Who are they?",
    "url": "https://www.pewresearch.org/fact-tank/2021/04/02/7-of-americans-dont-use-the-internet-who-are-they/",
    "upvotes": 232,
    "author": "ipsocannibal",
    "comments": 249,
    "link": "https://news.ycombinator.com/item?id=26719316"
  },
  {
    "title": "The Penguin Oil Industry",
    "url": "https://thetravellingcheetah.com/2019/04/07/a-glimpse-into-the-past-the-penguin-oil-industry/",
    "upvotes": 62,
    "author": "brudgers",
    "comments": 20,
    "link": "https://news.ycombinator.com/item?id=26705623"
  },
  {
    "title": "Joyce Project",
    "url": "https://www.joyceproject.com/pages/aboutproject.htm",
    "upvotes": 41,
    "author": "agarttha",
    "comments": 6,
    "link": "https://news.ycombinator.com/item?id=26688451"
  },
  {
    "title": "Tesorio",
    "url": "https://www.tesorio.com/careers#job-openings"
  },
  {
    "title": "First C compiler ported to GCC",
    "url": "https://github.com/vegesm/first-cc-gcc",
    "upvotes": 81,
    "author": "vegesm",
    "comments": 52,
    "link": "https://news.ycombinator.com/item?id=26697061"
  },
  {
    "title": "Show HN: DragonRuby Game Toolkit",
    "url": "http://dragonruby.org/toolkit/game",
    "upvotes": 184,
    "author": "amirrajan",
    "comments": 102,
    "link": "https://news.ycombinator.com/item?id=26719105"
  },
  {
    "title": "Ask HN: What tech job would let me get away with the least real work possible?",
    "url": "item?id=26721951",
    "upvotes": 224,
    "author": "lmueongoqx",
    "comments": 134,
    "link": "https://news.ycombinator.com/item?id=26721951"
  },
  {
    "title": "You can now turn on Nvidia's excellent noise cancellation with any GeForce GPU",
    "url": "https://www.pcgamer.com/nvidia-rtx-voice-noise-cancellation-geforce-gpu-supported/",
    "upvotes": 35,
    "author": "woliveirajr",
    "comments": 8,
    "link": "https://news.ycombinator.com/item?id=26723028"
  },
  {
    "title": "Animation of Electric Machines",
    "url": "http://people.ece.umn.edu/users/riaz/animations/listanimations.html",
    "upvotes": 88,
    "author": "agul29",
    "comments": 9,
    "link": "https://news.ycombinator.com/item?id=26696505"
  },
  {
    "title": "Lisp as an alternative to Java",
    "url": "https://norvig.com/java-lisp.html",
    "upvotes": 102,
    "author": "azhenley",
    "comments": 35,
    "link": "https://news.ycombinator.com/item?id=26720403"
  },
  {
    "title": "RFC 1: Host Software",
    "url": "https://tools.ietf.org/html/rfc1",
    "upvotes": 30,
    "author": "vages",
    "comments": 3,
    "link": "https://news.ycombinator.com/item?id=26721377"
  },
  {
    "title": "Show HN: AgoBrowse: Picture books for kids without distractions",
    "url": "https://bitbucket.org/BjornErlingFloetten/agobrowse",
    "upvotes": 36,
    "author": "AgoRapide",
    "comments": 23,
    "link": "https://news.ycombinator.com/item?id=26697285"
  },
  {
    "title": "Show HN: Skruv – No-dependency, no-build, small JavaScript framework",
    "url": "https://skruv.io/",
    "upvotes": 64,
    "author": "SahAssar",
    "comments": 74,
    "link": "https://news.ycombinator.com/item?id=26722051"
  },
  {
    "title": "Update on Git.php.net Incident",
    "url": "https://externals.io/message/113981",
    "upvotes": 93,
    "author": "gslin",
    "comments": 48,
    "link": "https://news.ycombinator.com/item?id=26720201"
  },
  {
    "title": "Bronze Age slab found in France is oldest 3D map in Europe",
    "url": "https://www.bbc.com/news/world-europe-56648055",
    "upvotes": 116,
    "author": "HenryBemis",
    "comments": 30,
    "link": "https://news.ycombinator.com/item?id=26717729"
  },
  {
    "title": "Anatoli Bugorski: The Man Who Stuck His Head Inside a Particle Accelerator",
    "url": "https://www.amusingplanet.com/2020/02/anatoli-bugorski-man-who-stuck-his-head.html",
    "upvotes": 79,
    "author": "spekcular",
    "comments": 42,
    "link": "https://news.ycombinator.com/item?id=26718582"
  },
  {
    "title": "From Academia to Startups – Common Founder Foibles",
    "url": "https://www.celinehh.com/academia-to-startups",
    "upvotes": 17,
    "author": "apsec112",
    "comments": 7,
    "link": "https://news.ycombinator.com/item?id=26707520"
  },
  {
    "title": "Jeff Bezos comes out in support of increased corporate taxes",
    "url": "https://www.cnn.com/2021/04/06/economy/amazon-jeff-bezos-corporate-tax-increase/index.html",
    "upvotes": 145,
    "author": "CharlesW",
    "comments": 225,
    "link": "https://news.ycombinator.com/item?id=26720295"
  },
  {
    "title": "Google’s copying of the Java SE API was fair use [pdf]",
    "url": "https://www.supremecourt.gov/opinions/20pdf/18-956_d18f.pdf",
    "upvotes": 4022,
    "author": "pdoconnell",
    "comments": 919,
    "link": "https://news.ycombinator.com/item?id=26699106"
  },
  {
    "title": "Wuffs’ PNG image decoder",
    "url": "https://nigeltao.github.io/blog/2021/fastest-safest-png-decoder.html",
    "upvotes": 428,
    "author": "est31",
    "comments": 120,
    "link": "https://news.ycombinator.com/item?id=26714831"
  },
  {
    "title": "Relighting and Color Grading with Machine Learning",
    "url": "https://martinanderson.substack.com/p/relighting-and-color-grading-with",
    "upvotes": 40,
    "author": "Hard_Space",
    "comments": 7,
    "link": "https://news.ycombinator.com/item?id=26696557"
  },
  {
    "title": "IntelliJ IDEA 2021.1 is Out",
    "url": "https://blog.jetbrains.com/idea/2021/04/intellij-idea-2021-1/",
    "upvotes": 9,
    "author": "programeris",
    "comments": null,
    "link": "https://news.ycombinator.com/item?id=26723010"
  },
  {
    "title": "Signal adds a payments feature with a privacy-focused cryptocurrency",
    "url": "https://www.wired.com/story/signal-mobilecoin-payments-messaging-cryptocurrency/",
    "upvotes": 481,
    "author": "josh2600",
    "comments": 556,
    "link": "https://news.ycombinator.com/item?id=26713827"
  },
  {
    "title": "Left-wing party opposed to rare earth mining project wins Greenland election",
    "url": "https://www.france24.com/en/europe/20210407-left-wing-party-opposed-to-rare-earth-mining-project-wins-greenland-election",
    "upvotes": 9,
    "author": "pseudolus",
    "comments": null,
    "link": "https://news.ycombinator.com/item?id=26722770"
  },
  {
    "title": "Rick Moody on How a Photograph Can Tell an Entire Story",
    "url": "https://lithub.com/rick-moody-on-how-a-photograph-can-tell-an-entire-story/",
    "upvotes": 5,
    "author": "prismatic",
    "comments": null,
    "link": "https://news.ycombinator.com/item?id=26704673"
  },
  {
    "title": "The antidote to civilisational collapse – An interview with Adam Curtis",
    "url": "https://www.economist.com/open-future/2018/12/06/the-antidote-to-civilisational-collapse",
    "upvotes": 142,
    "author": "marton78",
    "comments": 169,
    "link": "https://news.ycombinator.com/item?id=26721042"
  },
  {
    "title": "Eliminating Data Races in Firefox",
    "url": "https://hacks.mozilla.org/2021/04/eliminating-data-races-in-firefox-a-technical-report/",
    "upvotes": 447,
    "author": "caution",
    "comments": 116,
    "link": "https://news.ycombinator.com/item?id=26713037"
  },
  {
    "title": "Adjustable, low-impact keeb",
    "url": "https://hackaday.com/2021/04/02/adjustable-low-impact-keeb-is-about-as-comfortable-as-it-gets/",
    "upvotes": 87,
    "author": "serial_dev",
    "comments": 72,
    "link": "https://news.ycombinator.com/item?id=26696026"
  }
]
