[
  {
    "title": "Light Pollution Map",
    "url": "https://www.lightpollutionmap.info/",
    "upvotes": 105,
    "author": "okl",
    "comments": 51,
    "link": "https://news.ycombinator.com/item?id=26915536"
  },
  {
    "title": "Lego Microscope",
    "url": "https://github.com/tobetz/LegoMicroscope",
    "upvotes": 243,
    "author": "freddypaulo",
    "comments": 73,
    "link": "https://news.ycombinator.com/item?id=26914023"
  },
  {
    "title": "Cycles X",
    "url": "https://code.blender.org/2021/04/cycles-x/",
    "upvotes": 24,
    "author": "Tomte",
    "comments": 5,
    "link": "https://news.ycombinator.com/item?id=26916196"
  },
  {
    "title": "Convicted Post Office workers have names cleared after cover-up of flawed system",
    "url": "https://www.bbc.co.uk/news/business-56859357",
    "upvotes": 350,
    "author": "gerjomarty",
    "comments": 131,
    "link": "https://news.ycombinator.com/item?id=26913183"
  },
  {
    "title": "Semantic Satiation",
    "url": "https://en.wikipedia.org/wiki/Semantic_satiation",
    "upvotes": 25,
    "author": "annowiki",
    "comments": 12,
    "link": "https://news.ycombinator.com/item?id=26915742"
  },
  {
    "title": "Bye Aerospace Unveils 8-Seat All-Electric EFlyer 800",
    "url": "https://byeaerospace.com/bye-aerospace-unveils-8-seat-all-electric-eflyer-800/",
    "upvotes": 26,
    "author": "hindsightbias",
    "comments": 28,
    "link": "https://news.ycombinator.com/item?id=26915943"
  },
  {
    "title": "Why Lichess will always be free",
    "url": "https://lichess.org/blog/YF-ZORQAACAA89PI/why-lichess-will-always-be-free.",
    "upvotes": 1012,
    "author": "hydroxideOH-",
    "comments": 334,
    "link": "https://news.ycombinator.com/item?id=26910579"
  },
  {
    "title": "Digging for performance gold: finding hidden performance wins",
    "url": "https://blog.chromium.org/2021/04/digging-for-performance-gold.html",
    "upvotes": 46,
    "author": "markdog12",
    "comments": 15,
    "link": "https://news.ycombinator.com/item?id=26915022"
  },
  {
    "title": "Show HN: 100 paying users in 100 days",
    "url": "https://100in100.co/",
    "upvotes": 17,
    "author": "antcas",
    "comments": 5,
    "link": "https://news.ycombinator.com/item?id=26915739"
  },
  {
    "title": "Beej’s Guide to C Programming [pdf]",
    "url": "http://beej.us/guide/bgc/pdf/bgc_usl_c_1.pdf",
    "upvotes": 373,
    "author": "tumblewit",
    "comments": 120,
    "link": "https://news.ycombinator.com/item?id=26911399"
  },
  {
    "title": "Googling is one of the most important skills for every developer",
    "url": "https://markodenic.com/use-google-like-a-pro/",
    "upvotes": 250,
    "author": "sudo_overflow",
    "comments": 132,
    "link": "https://news.ycombinator.com/item?id=26911629"
  },
  {
    "title": "How “the king of the world’s booksellers” produced manuscripts",
    "url": "https://lithub.com/goatskin-tree-bark-and-one-expensive-scribe-how-the-king-of-the-worlds-booksellers-produced-manuscripts/?utm_source=Sailthru&utm_medium=email&utm_campaign=Lit%20Hub%20Daily:%20April%2013%2C%202021&utm_term=lithub_master_list",
    "upvotes": 19,
    "author": "seventyhorses",
    "comments": 2,
    "link": "https://news.ycombinator.com/item?id=26908279"
  },
  {
    "title": "Apple’s M1 Positioning Mocks the Entire x86 Business Model",
    "url": "https://www.extremetech.com/computing/322120-apples-m1-positioning-mocks-every-x86-cpu-amd-and-intel-have-ever-launched",
    "upvotes": 457,
    "author": "danaris",
    "comments": 650,
    "link": "https://news.ycombinator.com/item?id=26910193"
  },
  {
    "title": "Great Malaria Vaccine News",
    "url": "https://blogs.sciencemag.org/pipeline/archives/2021/04/23/great-malaria-vaccine-news",
    "upvotes": 12,
    "author": "hprotagonist",
    "comments": null,
    "link": "https://news.ycombinator.com/item?id=26916237"
  },
  {
    "title": "Ambition",
    "url": "https://ambition.com/career/opportunity/full-stack-engineer/"
  },
  {
    "title": "How to Interchange Ed25119 Keys",
    "url": "https://www.tbray.org/ongoing/When/202x/2021/04/19/PKI-Detective",
    "upvotes": 44,
    "author": "tmfi",
    "comments": 39,
    "link": "https://news.ycombinator.com/item?id=26913756"
  },
  {
    "title": "Vizy, an AI Camera for the Pi",
    "url": "https://vizycam.com/",
    "upvotes": 4,
    "author": "kordlessagain",
    "comments": null,
    "link": "https://news.ycombinator.com/item?id=26916274"
  },
  {
    "title": "Bugs allowed hackers to dox John Deere tractor owners",
    "url": "https://www.vice.com/en/article/4avy8j/bugs-allowed-hackers-to-dox-all-john-deere-owners",
    "upvotes": 216,
    "author": "arkadiyt",
    "comments": 51,
    "link": "https://news.ycombinator.com/item?id=26903482"
  },
  {
    "title": "'World’s most powerful' tidal turbine sets sail from Dundee",
    "url": "https://www.bbc.co.uk/news/uk-scotland-tayside-central-56818538",
    "upvotes": 97,
    "author": "Kaibeezy",
    "comments": 65,
    "link": "https://news.ycombinator.com/item?id=26912347"
  },
  {
    "title": "Apple Is Sued for Telling You That You're “Buying” Movies",
    "url": "https://nofilmschool.com/apple-movie-buys",
    "upvotes": 478,
    "author": "paulcarroty",
    "comments": 313,
    "link": "https://news.ycombinator.com/item?id=26912118"
  },
  {
    "title": "Game Accessibility Guidelines",
    "url": "http://gameaccessibilityguidelines.com/",
    "upvotes": 32,
    "author": "robin_reala",
    "comments": 14,
    "link": "https://news.ycombinator.com/item?id=26913554"
  },
  {
    "title": "NASA’s bold bet on Starship for the Moon may change spaceflight forever",
    "url": "https://arstechnica.com/science/2021/04/five-reasons-why-nasas-starship-award-is-a-watershed-moment-in-spaceflight/",
    "upvotes": 47,
    "author": "alexrustic",
    "comments": 15,
    "link": "https://news.ycombinator.com/item?id=26915196"
  },
  {
    "title": "The Boyer-Moore Fast String Searching Algorithm",
    "url": "https://www.cs.utexas.edu/users/moore/best-ideas/string-searching/",
    "upvotes": 171,
    "author": "js2",
    "comments": 60,
    "link": "https://news.ycombinator.com/item?id=26910982"
  },
  {
    "title": "The Last Generation of Typewriter Repairmen",
    "url": "https://www.wired.com/2010/05/gallery-typewriters/",
    "upvotes": 9,
    "author": "Tomte",
    "comments": 3,
    "link": "https://news.ycombinator.com/item?id=26913461"
  },
  {
    "title": "4chan founder Chris Poole leaves Google",
    "url": "https://arstechnica.com/gadgets/2021/04/4chan-founder-chris-poole-leaves-google/",
    "upvotes": 8,
    "author": "b5",
    "comments": null,
    "link": "https://news.ycombinator.com/item?id=26916383"
  },
  {
    "title": "What They Wrote About the War",
    "url": "https://www.lareviewofbooks.org/article/what-they-wrote-about-the-war/",
    "upvotes": 4,
    "author": "lermontov",
    "comments": null,
    "link": "https://news.ycombinator.com/item?id=26911433"
  },
  {
    "title": "Some useful regular expressions for programmers",
    "url": "https://lemire.me/blog/2021/04/22/some-useful-regular-expressions-for-programmers/",
    "upvotes": 128,
    "author": "zdw",
    "comments": 48,
    "link": "https://news.ycombinator.com/item?id=26910717"
  },
  {
    "title": "Wirecard employees removed millions in cash using shopping bags",
    "url": "https://www.ft.com/content/31a8ed93-f602-47f0-9120-4b4f152ec7bc",
    "upvotes": 47,
    "author": "doener",
    "comments": 23,
    "link": "https://news.ycombinator.com/item?id=26915388"
  },
  {
    "title": "Headless WYSISWYG Text Editor – tiptap editor",
    "url": "https://www.tiptap.dev/",
    "upvotes": 163,
    "author": "me_bx",
    "comments": 100,
    "link": "https://news.ycombinator.com/item?id=26901975"
  },
  {
    "title": "Moving Forth",
    "url": "https://www.bradrodriguez.com/papers/moving1.htm",
    "upvotes": 59,
    "author": "tosh",
    "comments": 7,
    "link": "https://news.ycombinator.com/item?id=26900401"
  }
]
